q_materialise/__init__.py
q_materialise/binding.py
q_materialise/colors.py
q_materialise/core.py
q_materialise/demo.py
q_materialise/style.py
q_materialise/utils.py
q_materialise/icons/downarrow.svg
q_materialise/icons/infoicon.svg
q_materialise/icons/uparrow.svg
q_materialise/styles/__init__.py
q_materialise/styles/crimson_depth.json
q_materialise/styles/crimson_glow.json
q_materialise/styles/dark_blue.json
q_materialise/styles/dark_teal.json
q_materialise/styles/emerald_morning.json
q_materialise/styles/emerald_nightfall.json
q_materialise/styles/forest_dusk.json
q_materialise/styles/forest_mist.json
q_materialise/styles/golden_morn.json
q_materialise/styles/golden_shadows.json
q_materialise/styles/indigo_dawn.json
q_materialise/styles/indigo_twilight.json
q_materialise/styles/lagoon_daybreak.json
q_materialise/styles/lagoon_midnight.json
q_materialise/styles/light_blue.json
q_materialise/styles/light_teal.json
q_materialise/styles/plum_breeze.json
q_materialise/styles/plum_eclipse.json
q_materialise/styles/rose_blossom.json
q_materialise/styles/rose_mystique.json
q_materialise/styles/sapphire_day.json
q_materialise/styles/sapphire_night.json
q_materialise/styles/tangerine_dusk.json
q_materialise/styles/tangerine_morning.json
q_materialise-0.1.8.dist-info/licenses/LICENSE
q_materialise-0.1.8.dist-info/METADATA
q_materialise-0.1.8.dist-info/WHEEL
q_materialise-0.1.8.dist-info/top_level.txt
q_materialise-0.1.8.dist-info/RECORD
