Metadata-Version: 2.4
Name: q-materialise
Version: 0.1.8
Summary: An enhanced Material Design stylesheet library for Qt (PyQt5, PyQt6, PySide2 and PySide6)
Author-email: "Lewis (arched.dev)" <lewis@arched.dev>
License: MIT License
Keywords: qt,material,stylesheet,style,gui,pyqt,pyside
Requires-Python: >=3.8
License-File: LICENSE
Requires-Dist: packaging>=20.0
Provides-Extra: pyqt5
Requires-Dist: PyQt5>=5.15; extra == "pyqt5"
Provides-Extra: pyqt6
Requires-Dist: PyQt6>=6.0; extra == "pyqt6"
Provides-Extra: pyside2
Requires-Dist: PySide2>=5.15; extra == "pyside2"
Provides-Extra: pyside6
Requires-Dist: PySide6>=6.0; extra == "pyside6"
Provides-Extra: docs
Requires-Dist: sphinx<8.2,>=7.2; python_version < "3.11" and extra == "docs"
Requires-Dist: sphinx>=8.2; python_version >= "3.11" and extra == "docs"
Requires-Dist: myst-parser>=2; extra == "docs"
Requires-Dist: sphinx-autodoc-typehints>=2; extra == "docs"
Dynamic: license-file
